paranormal/__init__.py
paranormal/parameter_interface.py
paranormal/params.py
paranormal/test/test_parameter_interface.py
paranormal/test/test_params.py
paranormal/units.py
paranormal-0.2.3.dist-info/LICENSE
paranormal-0.2.3.dist-info/WHEEL
paranormal-0.2.3.dist-info/METADATA
paranormal-0.2.3.dist-info/RECORD
