Metadata-Version: 2.1
Name: paranormal
Version: 0.2.3
Summary: Coherent management of large parameter lists in Python
License: Apache-2.0
Author: Schuyler Fried
Author-email: schuylerfried@gmail.com
Requires-Python: >3.6
Classifier: License :: OSI Approved :: Apache Software License
Classifier: Programming Language :: Python :: 3
Classifier: Programming Language :: Python :: 3.7
Classifier: Programming Language :: Python :: 3.8
Classifier: Programming Language :: Python :: 3.9
Requires-Dist: PyYAML (>=5.1)
Requires-Dist: numpy (>1.18)
Requires-Dist: pampy (>=0.2.1)
